django_linkedin_posts/__init__.py
django_linkedin_posts/admin.py
django_linkedin_posts/apps.py
django_linkedin_posts/exceptions.py
django_linkedin_posts/models.py
django_linkedin_posts/migrations/0010_initial.py
django_linkedin_posts/migrations/0011_post_created_at_post_updated_at.py
django_linkedin_posts/migrations/0012_comment_created_at_comment_updated_at_and_more.py
django_linkedin_posts/migrations/0013_rename_comment_poll_comment_text_and_more.py
django_linkedin_posts/migrations/0014_rename_image_title_postimage_title_and_more.py
django_linkedin_posts/migrations/0015_comment_poll_alter_comment_post_alter_comment_text.py
django_linkedin_posts/migrations/__init__.py
django_linkedin_posts-0.0.4.dist-info/LICENSE
django_linkedin_posts-0.0.4.dist-info/METADATA
django_linkedin_posts-0.0.4.dist-info/WHEEL
django_linkedin_posts-0.0.4.dist-info/top_level.txt
django_linkedin_posts-0.0.4.dist-info/RECORD
