Metadata-Version: 2.1
Name: django-linkedin-posts
Version: 0.0.4
Summary: An app to manage Linkedin posts in a Django project
Author-email: Rami <ramiboutas@protonmail.com>
Project-URL: Homepage, https://github.com/ramiboutas/django-linkedin-posts
Project-URL: Bug Tracker, https://github.com/ramiboutas/django-linkedin-posts/issues
Classifier: Programming Language :: Python :: 3
Classifier: License :: OSI Approved :: MIT License
Classifier: Operating System :: OS Independent
Classifier: Framework :: Django
Classifier: Framework :: Django :: 4
Requires-Python: >=3.7
License-File: LICENSE
Requires-Dist: linkedin-posts
Requires-Dist: pillow
Requires-Dist: django
